pyhough/__init__.py
pyhough/gfh.py
pyhough/hm.py
pyhough/physics.py
pyhough/pm.py
pyhough-0.0.10.dist-info/METADATA
pyhough-0.0.10.dist-info/WHEEL
pyhough-0.0.10.dist-info/licenses/LICENSE
pyhough-0.0.10.dist-info/RECORD
