Metadata-Version: 2.4
Name: pyhough
Version: 0.0.10
Summary: Package to compute the Frequency-Hough Transform to search for continuous gravitational waves in LIGO, Virgo and KAGRA data
Project-URL: Homepage, https://github.com/andrew-l-miller/pyhough
Project-URL: Issues, https://github.com/andrew-l-miller/pyhough/issues
Project-URL: Documentation, https://github.com/andrew-l-miller/pyhough#readme
Project-URL: DOI, https://doi.org/10.5281/zenodo.15512454
Author-email: "Andrew L. Miller" <andrew.miller.ligo@gmail.com>
License-Expression: MIT AND (Apache-2.0 OR BSD-2-Clause)
License-File: LICENSE
Classifier: License :: OSI Approved :: MIT License
Classifier: Operating System :: OS Independent
Classifier: Programming Language :: Python :: 3
Requires-Python: >=3.8
Requires-Dist: matplotlib
Requires-Dist: numpy
Requires-Dist: pyfstat
